{
	"semanticHighlighting": "true",
	"name": "purple-300-60-light",
	"tokenColors": [
		{
			"name": "Keyword, storage, tag",
			"scope": [
				"keyword",
				"storage",
				"entity.name.tag"
			],
			"settings": {
				"foreground": "#705a49"
			}
		},
		{
			"name": "HTML tag",
			"scope": [
				"entity.name.tag.html"
			],
			"settings": {
				"foreground": "#342371"
			}
		},
		{
			"name": "CSS Tag",
			"scope": [
				"entity.name.tag.css"
			],
			"settings": {
				"foreground": "#6751a6"
			}
		},
		{
			"name": "Storage type, attribute",
			"scope": [
				"storage.type",
				"entity.other.attribute-name"
			],
			"settings": {
				"fontStyle": "italic",
				"foreground": "#705a49"
			}
		},
		{
			"name": "Entity",
			"scope": [
				"entity.name",
				"entity.other.inherited-class"
			],
			"settings": {
				"foreground": "#3f2c1e"
			}
		},
		{
			"name": "Library entity",
			"scope": "support",
			"settings": {
				"fontStyle": "italic",
				"foreground": "#3f2c1e"
			}
		},
		{
			"name": "Variable",
			"scope": [
				"variable",
				"variable.language",
				"variable.parameter"
			],
			"settings": {
				"foreground": "#4c4262"
			}
		},
		{
			"name": "Library variable",
			"scope": [
				"support.variable",
				"support.other.variable"
			],
			"settings": {
				"foreground": "#4c4262"
			}
		},
		{
			"name": "Constant",
			"scope": [
				"constant",
				"constant.numeric",
				"constant.language",
				"constant.character.escape",
				"constant.other",
				"keyword.other.unit.px.css"
			],
			"settings": {
				"foreground": "#342371"
			}
		},
		{
			"name": "Library constant",
			"scope": "support.constant",
			"settings": {
				"fontStyle": "",
				"foreground": "#342371"
			}
		},
		{
			"name": "String",
			"scope": "string",
			"settings": {
				"foreground": "#6751a6"
			}
		},
		{
			"name": "Comment",
			"scope": "comment",
			"settings": {
				"fontStyle": "italic",
				"foreground": "#7d7295"
			}
		},
		{
			"name": "Diff delete",
			"scope": "markup.deleted",
			"settings": {
				"foreground": "#a13a38"
			}
		},
		{
			"name": "Diff insert",
			"scope": "markup.inserted",
			"settings": {
				"foreground": "#006f32"
			}
		},
		{
			"name": "Diff change",
			"scope": "markup.changed",
			"settings": {
				"foreground": "#0061b1"
			}
		},
		{
			"name": "Markup heading",
			"scope": [
				"markup.heading",
				"entity.name.section"
			],
			"settings": {
				"foreground": "#342371"
			}
		},
		{
			"name": "Markup styling",
			"scope": [
				"markup.bold",
				"markup.italic",
				"markup.underline"
			],
			"settings": {
				"foreground": "#6751a6"
			}
		},
		{
			"name": "Markup quote",
			"scope": [
				"markup.quote",
				"markup.raw.inline",
				"markup.raw.block"
			],
			"settings": {
				"foreground": "#7d7295"
			}
		},
		{
			"name": "Invalid",
			"scope": "invalid",
			"settings": {
				"foreground": "#a13a38"
			}
		}
	],
	"semanticTokenColors": {
		"method.declaration": {
			"foreground": "#291705",
			"bold": "true"
		},
		"function.declaration": {
			"foreground": "#291705",
			"bold": "true"
		}
	},
	"colors": {
		"gitDecoration.untrackedResourceForeground": "#006f32",
		"list.inactiveSelectionBackground": "#d4d4d4",
		"focusBorder": "#9c86cecc",
		"terminal.background": "#f1f1f1",
		"button.background": "#a697c5",
		"editorOverviewRuler.deletedForeground": "#a13a3899",
		"editor.background": "#f1f1f1",
		"statusBar.noFolderBackground": "#c6c6c6",
		"editorCursor.foreground": "#3f2c1e",
		"editorOverviewRuler.rangeHighlightForeground": "#0061b199",
		"diffEditor.insertedTextBackground": "#006f3233",
		"terminal.ansiBrightBlue": "#897261",
		"peekViewEditor.background": "#e2e2e266",
		"widget.shadow": "#ffffff5c",
		"editorError.foreground": "#a13a38",
		"terminal.ansiRed": "#352c4a",
		"terminal.ansiBrightCyan": "#584e6e",
		"terminal.ansiYellow": "#342371",
		"sideBarSectionHeader.background": "#d4d4d4",
		"terminal.ansiGreen": "#5a4598",
		"editor.findMatchBorder": "#6751a6",
		"input.placeholderForeground": "#705a49",
		"input.foreground": "#3f2c1e",
		"activityBarBadge.foreground": "#291705",
		"debugToolBar.background": "#d4d4d4",
		"badge.foreground": "#291705",
		"editorOverviewRuler.incomingContentForeground": "#0061b180",
		"peekViewResult.fileForeground": "#291705",
		"button.hoverBackground": "#9385b2",
		"peekViewEditor.matchHighlightBackground": "#cec1e7",
		"editorOverviewRuler.border": "#705a494d",
		"list.highlightForeground": "#291705",
		"terminal.ansiBrightYellow": "#342371",
		"peekViewResult.background": "#e2e2e2",
		"editor.linkedEditingBackground": "#7d72954d",
		"terminal.ansiBrightMagenta": "#8269c1",
		"diffEditor.removedTextBackground": "#ff000033",
		"badge.background": "#b9b9b9",
		"editorGroupHeader.noTabsBackground": "#f1f1f1",
		"editorHoverWidget.background": "#e2e2e2",
		"editor.lineHighlightBorder": "#e2e2e2",
		"titleBar.activeBackground": "#b9b9b9",
		"editorOverviewRuler.wordHighlightStrongForeground": "#3f2c1ecc",
		"statusBar.background": "#c6c6c6",
		"editor.findRangeHighlightBackground": "#c6c6c666",
		"editorLink.activeForeground": "#6751a6",
		"statusBarItem.hoverBackground": "#b9b9b9",
		"foreground": "#3f2c1e",
		"sideBarTitle.foreground": "#3f2c1e",
		"terminal.ansiCyan": "#584e6e",
		"scrollbarSlider.background": "#b9b9b980",
		"inputValidation.warningBorder": "#8d4d13",
		"peekViewTitleDescription.foreground": "#3f2c1eb3",
		"inputValidation.errorBorder": "#a13a38",
		"inputValidation.warningBackground": "#e2bfa7",
		"merge.currentHeaderBackground": "#006f3280",
		"editorGutter.addedBackground": "#006f32",
		"editorGutter.background": "#f1f1f1",
		"gitDecoration.modifiedResourceForeground": "#8d4d13",
		"editor.inactiveSelectionBackground": "#c6c6c6a4",
		"textLink.foreground": "#6751a6",
		"statusBar.debuggingForeground": "#291705",
		"terminal.ansiBlue": "#897261",
		"editorWhitespace.foreground": "#a48c7a",
		"terminal.foreground": "#3f2c1e",
		"peekViewTitle.background": "#e2e2e266",
		"activityBarBadge.background": "#a697c5",
		"tab.activeBackground": "#f1f1f1",
		"editorGroup.dropBackground": "#b9b9b980",
		"editorSuggestWidget.selectedBackground": "#d4d4d4",
		"panel.border": "#705a4959",
		"gitDecoration.conflictingResourceForeground": "#0061b1",
		"editorOverviewRuler.currentContentForeground": "#3f2c1e80",
		"panelTitle.activeForeground": "#291705",
		"tab.border": "#f1f1f1",
		"editorOverviewRuler.wordHighlightForeground": "#705a49cc",
		"editor.hoverHighlightBackground": "#b9b9b940",
		"textLink.activeForeground": "#6751a6",
		"gitDecoration.deletedResourceForeground": "#a13a38",
		"editor.wordHighlightBackground": "#6751a630",
		"button.foreground": "#291705",
		"editorOverviewRuler.selectionHighlightForeground": "#705a49cc",
		"gitDecoration.ignoredResourceForeground": "#705a49",
		"scrollbarSlider.activeBackground": "#705a4980",
		"titleBar.activeForeground": "#291705",
		"terminal.ansiBrightWhite": "#180000",
		"inputValidation.infoBackground": "#b7c7ec",
		"editorSuggestWidget.highlightForeground": "#6751a6",
		"terminal.ansiBrightBlack": "#897261",
		"editorWidget.background": "#e2e2e2",
		"editorSuggestWidget.background": "#e2e2e2",
		"editorOverviewRuler.modifiedForeground": "#0061b199",
		"terminal.ansiBrightGreen": "#5a4598",
		"peekViewResult.matchHighlightBackground": "#cec1e7",
		"terminal.ansiBlack": "#ffffff",
		"merge.currentContentBackground": "#006f3233",
		"editorGutter.modifiedBackground": "#0061b1",
		"descriptionForeground": "#3f2c1eb3",
		"editorGroup.emptyBackground": "#f1f1f1",
		"editor.wordHighlightStrongBackground": "#9b592030",
		"peekView.border": "#6751a6",
		"editorGroupHeader.tabsBackground": "#e2e2e2",
		"extensionButton.prominentBackground": "#9c86ce",
		"errorForeground": "#a13a38",
		"editor.lineHighlightBackground": "#e2e2e2",
		"merge.incomingHeaderBackground": "#0061b180",
		"peekViewResult.selectionBackground": "#6751a633",
		"editorSuggestWidget.border": "#f1f1f1",
		"activityBar.foreground": "#291705",
		"peekViewTitleLabel.foreground": "#291705",
		"extensionButton.prominentHoverBackground": "#9681c9",
		"activityBar.background": "#c6c6c6",
		"tab.unfocusedInactiveForeground": "#29170540",
		"inputValidation.infoBorder": "#0061b1",
		"merge.incomingContentBackground": "#0061b133",
		"titleBar.inactiveForeground": "#3f2c1e",
		"sideBar.background": "#e2e2e2",
		"list.activeSelectionBackground": "#d4d4d4",
		"inputValidation.errorBackground": "#ebbbb5",
		"terminal.ansiBrightRed": "#352c4a",
		"titleBar.inactiveBackground": "#b9b9b9",
		"editorLineNumber.activeForeground": "#3f2c1e",
		"editorOverviewRuler.infoForeground": "#0061b1",
		"input.background": "#f1f1f1",
		"editorInfo.foreground": "#342371",
		"dropdown.foreground": "#291705",
		"peekViewResult.selectionForeground": "#291705",
		"selection.background": "#9e9e9e80",
		"editor.selectionBackground": "#c6c6c6",
		"editorOverviewRuler.warningForeground": "#8d4d13",
		"editorBracketMatch.background": "#9e9e9e1a",
		"editorIndentGuide.background": "#c6c6c6",
		"inputOption.activeBorder": "#6751a600",
		"editorOverviewRuler.addedForeground": "#006f3299",
		"terminal.ansiMagenta": "#8269c1",
		"editorLineNumber.foreground": "#a48c7a",
		"list.focusBackground": "#c6c6c6",
		"tab.unfocusedActiveForeground": "#29170580",
		"editor.findMatchHighlightBackground": "#cec1e7",
		"editor.selectionHighlightBackground": "#4c426218",
		"editorBracketMatch.border": "#705a49",
		"list.activeSelectionForeground": "#291705",
		"editorGutter.deletedBackground": "#a13a38",
		"scrollbar.shadow": "#ffffff",
		"editorSuggestWidget.foreground": "#291705",
		"statusBar.foreground": "#3f2c1e",
		"list.hoverBackground": "#d4d4d4",
		"editorOverviewRuler.errorForeground": "#a13a38b3",
		"editorOverviewRuler.findMatchForeground": "#8d4d137e",
		"statusBar.debuggingBackground": "#c6c6c6",
		"editorOverviewRuler.commonContentForeground": "#705a4966",
		"progressBar.background": "#9d83de",
		"list.inactiveSelectionForeground": "#291705",
		"editorGroup.border": "#a48c7a",
		"tab.inactiveForeground": "#29170580",
		"editorCodeLens.foreground": "#3f2c1e",
		"list.dropBackground": "#c6c6c6",
		"editorUnnecessaryCode.opacity": "#ffffffc0",
		"editorWarning.foreground": "#8d4d13",
		"editor.findMatchBackground": "#b3a4d3",
		"tab.inactiveBackground": "#d4d4d4",
		"editorRuler.foreground": "#a48c7a",
		"editorIndentGuide.activeBackground": "#9e9e9e",
		"editorWidget.border": "#b9b9b9",
		"tab.activeForeground": "#291705",
		"notifications.background": "#e2e2e2",
		"terminal.ansiWhite": "#291705",
		"peekViewEditorGutter.background": "#e2e2e266",
		"dropdown.background": "#e2e2e2",
		"icon.foreground": "#3f2c1e",
		"scrollbarSlider.hoverBackground": "#9e9e9e80",
		"editor.foreground": "#3f2c1e",
		"editorHoverWidget.border": "#f1f1f1"
	}
}